[
	{
		"name": "chaos-knight",
		"adv": 3.2349,
		"winRate": 49.7785
	},
	{
		"name": "axe",
		"adv": 2.8346,
		"winRate": 48.8717
	},
	{
		"name": "spectre",
		"adv": 2.7196,
		"winRate": 44.3562
	},
	{
		"name": "clockwerk",
		"adv": 2.1304,
		"winRate": 50.8863
	},
	{
		"name": "templar-assassin",
		"adv": 2.0298,
		"winRate": 53.2352
	},
	{
		"name": "sand-king",
		"adv": 1.8314,
		"winRate": 51.8909
	},
	{
		"name": "treant-protector",
		"adv": 1.6639,
		"winRate": 49.1524
	},
	{
		"name": "winter-wyvern",
		"adv": 1.644,
		"winRate": 55.9642
	},
	{
		"name": "crystal-maiden",
		"adv": 1.4372,
		"winRate": 46.8965
	},
	{
		"name": "pudge",
		"adv": 1.3691,
		"winRate": 49.9849
	},
	{
		"name": "phantom-assassin",
		"adv": 1.3124,
		"winRate": 48.2397
	},
	{
		"name": "terrorblade",
		"adv": 1.3022,
		"winRate": 50.9921
	},
	{
		"name": "necrophos",
		"adv": 1.2948,
		"winRate": 45.9549
	},
	{
		"name": "earthshaker",
		"adv": 1.274,
		"winRate": 50.7367
	},
	{
		"name": "magnus",
		"adv": 1.2627,
		"winRate": 55.729
	},
	{
		"name": "slardar",
		"adv": 1.1732,
		"winRate": 52.2841
	},
	{
		"name": "techies",
		"adv": 1.1554,
		"winRate": 51.3017
	},
	{
		"name": "sven",
		"adv": 1.1447,
		"winRate": 50.9891
	},
	{
		"name": "venomancer",
		"adv": 1.0846,
		"winRate": 49.4463
	},
	{
		"name": "slark",
		"adv": 1.0719,
		"winRate": 53.0506
	},
	{
		"name": "warlock",
		"adv": 1.0221,
		"winRate": 49.1019
	},
	{
		"name": "lich",
		"adv": 0.9458,
		"winRate": 48.0571
	},
	{
		"name": "phantom-lancer",
		"adv": 0.9194,
		"winRate": 55.0347
	},
	{
		"name": "dark-seer",
		"adv": 0.8375,
		"winRate": 52.4701
	},
	{
		"name": "wraith-king",
		"adv": 0.834,
		"winRate": 44.366
	},
	{
		"name": "tiny",
		"adv": 0.7682,
		"winRate": 56.3739
	},
	{
		"name": "visage",
		"adv": 0.6742,
		"winRate": 54.5032
	},
	{
		"name": "dragon-knight",
		"adv": 0.6223,
		"winRate": 49.8434
	},
	{
		"name": "vengeful-spirit",
		"adv": 0.6215,
		"winRate": 48.3432
	},
	{
		"name": "shadow-demon",
		"adv": 0.5697,
		"winRate": 57.6437
	},
	{
		"name": "spirit-breaker",
		"adv": 0.5373,
		"winRate": 46.2554
	},
	{
		"name": "monkey-king",
		"adv": 0.5157,
		"winRate": 57.1066
	},
	{
		"name": "lion",
		"adv": 0.4915,
		"winRate": 52.1075
	},
	{
		"name": "zeus",
		"adv": 0.4695,
		"winRate": 43.549
	},
	{
		"name": "mirana",
		"adv": 0.4668,
		"winRate": 51.4468
	},
	{
		"name": "beastmaster",
		"adv": 0.4292,
		"winRate": 54.6794
	},
	{
		"name": "dazzle",
		"adv": 0.4237,
		"winRate": 49.843
	},
	{
		"name": "legion-commander",
		"adv": 0.355,
		"winRate": 50.7336
	},
	{
		"name": "shadow-fiend",
		"adv": 0.353,
		"winRate": 50.3382
	},
	{
		"name": "outworld-devourer",
		"adv": 0.3235,
		"winRate": 52.4891
	},
	{
		"name": "puck",
		"adv": 0.2845,
		"winRate": 57.3787
	},
	{
		"name": "omniknight",
		"adv": 0.2534,
		"winRate": 45.9407
	},
	{
		"name": "undying",
		"adv": 0.25,
		"winRate": 50.0682
	},
	{
		"name": "rubick",
		"adv": 0.2399,
		"winRate": 54.7168
	},
	{
		"name": "tusk",
		"adv": 0.1556,
		"winRate": 58.2195
	},
	{
		"name": "centaur-warrunner",
		"adv": 0.0374,
		"winRate": 46.0766
	},
	{
		"name": "medusa",
		"adv": 0.0107,
		"winRate": 51.1675
	},
	{
		"name": "shadow-shaman",
		"adv": -0.0039,
		"winRate": 47.969
	},
	{
		"name": "witch-doctor",
		"adv": -0.0135,
		"winRate": 49.0441
	},
	{
		"name": "enigma",
		"adv": -0.0188,
		"winRate": 47.4316
	},
	{
		"name": "batrider",
		"adv": -0.0511,
		"winRate": 57.7058
	},
	{
		"name": "tidehunter",
		"adv": -0.0668,
		"winRate": 49.4056
	},
	{
		"name": "ancient-apparition",
		"adv": -0.0696,
		"winRate": 49.6701
	},
	{
		"name": "luna",
		"adv": -0.0703,
		"winRate": 48.1497
	},
	{
		"name": "windranger",
		"adv": -0.0883,
		"winRate": 54.3731
	},
	{
		"name": "ogre-magi",
		"adv": -0.0911,
		"winRate": 48.4496
	},
	{
		"name": "brewmaster",
		"adv": -0.1051,
		"winRate": 52.3932
	},
	{
		"name": "kunkka",
		"adv": -0.1269,
		"winRate": 55.5879
	},
	{
		"name": "disruptor",
		"adv": -0.1345,
		"winRate": 49.9975
	},
	{
		"name": "invoker",
		"adv": -0.1391,
		"winRate": 51.7337
	},
	{
		"name": "faceless-void",
		"adv": -0.1632,
		"winRate": 50.9028
	},
	{
		"name": "bounty-hunter",
		"adv": -0.2083,
		"winRate": 52.0016
	},
	{
		"name": "razor",
		"adv": -0.2127,
		"winRate": 55.1202
	},
	{
		"name": "lycan",
		"adv": -0.252,
		"winRate": 47.8022
	},
	{
		"name": "underlord",
		"adv": -0.2661,
		"winRate": 46.8398
	},
	{
		"name": "gyrocopter",
		"adv": -0.4035,
		"winRate": 56.3826
	},
	{
		"name": "bristleback",
		"adv": -0.4057,
		"winRate": 47.1636
	},
	{
		"name": "timbersaw",
		"adv": -0.478,
		"winRate": 52.3318
	},
	{
		"name": "naga-siren",
		"adv": -0.5407,
		"winRate": 54.6834
	},
	{
		"name": "jakiro",
		"adv": -0.581,
		"winRate": 46.5323
	},
	{
		"name": "riki",
		"adv": -0.6223,
		"winRate": 44.5131
	},
	{
		"name": "lifestealer",
		"adv": -0.6492,
		"winRate": 52.326
	},
	{
		"name": "storm-spirit",
		"adv": -0.7119,
		"winRate": 50.7346
	},
	{
		"name": "earth-spirit",
		"adv": -0.7201,
		"winRate": 58.0396
	},
	{
		"name": "ember-spirit",
		"adv": -0.7298,
		"winRate": 51.4188
	},
	{
		"name": "queen-of-pain",
		"adv": -0.7459,
		"winRate": 55.75
	},
	{
		"name": "viper",
		"adv": -0.7852,
		"winRate": 50.0813
	},
	{
		"name": "tinker",
		"adv": -0.7891,
		"winRate": 50.2895
	},
	{
		"name": "skywrath-mage",
		"adv": -0.8177,
		"winRate": 50.8478
	},
	{
		"name": "abaddon",
		"adv": -0.8941,
		"winRate": 44.1273
	},
	{
		"name": "elder-titan",
		"adv": -0.9822,
		"winRate": 47.9113
	},
	{
		"name": "pugna",
		"adv": -1.0267,
		"winRate": 51.5651
	},
	{
		"name": "doom",
		"adv": -1.036,
		"winRate": 55.8582
	},
	{
		"name": "keeper-of-the-light",
		"adv": -1.061,
		"winRate": 50.7066
	},
	{
		"name": "death-prophet",
		"adv": -1.2419,
		"winRate": 52.2741
	},
	{
		"name": "lone-druid",
		"adv": -1.2641,
		"winRate": 59.0614
	},
	{
		"name": "night-stalker",
		"adv": -1.2997,
		"winRate": 49.1682
	},
	{
		"name": "weaver",
		"adv": -1.3502,
		"winRate": 48.7236
	},
	{
		"name": "nyx-assassin",
		"adv": -1.4436,
		"winRate": 49.1639
	},
	{
		"name": "leshrac",
		"adv": -1.4746,
		"winRate": 54.3966
	},
	{
		"name": "alchemist",
		"adv": -1.5253,
		"winRate": 54.0414
	},
	{
		"name": "meepo",
		"adv": -1.5855,
		"winRate": 55.3466
	},
	{
		"name": "sniper",
		"adv": -1.5883,
		"winRate": 48.3734
	},
	{
		"name": "bloodseeker",
		"adv": -1.6118,
		"winRate": 47.1916
	},
	{
		"name": "ursa",
		"adv": -1.641,
		"winRate": 44.9267
	},
	{
		"name": "bane",
		"adv": -1.6436,
		"winRate": 53.9214
	},
	{
		"name": "natures-prophet",
		"adv": -1.7117,
		"winRate": 54.2255
	},
	{
		"name": "morphling",
		"adv": -1.7223,
		"winRate": 53.0434
	},
	{
		"name": "broodmother",
		"adv": -1.7277,
		"winRate": 58.2533
	},
	{
		"name": "juggernaut",
		"adv": -1.808,
		"winRate": 48.9371
	},
	{
		"name": "enchantress",
		"adv": -1.8459,
		"winRate": 55.2746
	},
	{
		"name": "silencer",
		"adv": -2,
		"winRate": 45.6687
	},
	{
		"name": "drow-ranger",
		"adv": -2.0174,
		"winRate": 48.7
	},
	{
		"name": "lina",
		"adv": -2.0586,
		"winRate": 50.6264
	},
	{
		"name": "chen",
		"adv": -2.0619,
		"winRate": 56.7917
	},
	{
		"name": "troll-warlord",
		"adv": -2.4435,
		"winRate": 43.9102
	},
	{
		"name": "oracle",
		"adv": -2.5127,
		"winRate": 57.9241
	},
	{
		"name": "io",
		"adv": -2.7037,
		"winRate": 61.5698
	},
	{
		"name": "arc-warden",
		"adv": -2.8984,
		"winRate": 53.3555
	},
	{
		"name": "clinkz",
		"adv": -3.2999,
		"winRate": 50.0629
	},
	{
		"name": "huskar",
		"adv": -3.6048,
		"winRate": 52.0167
	},
	{
		"name": "anti-mage",
		"adv": -4.0266,
		"winRate": 47.8745
	}
]